hybridbackend/libhybridbackend.so
hybridbackend/__init__.py
hybridbackend/run.py
hybridbackend/common/test.py
hybridbackend/common/__init__.py
hybridbackend/torch/__init__.py
hybridbackend/tensorflow/wraps.py
hybridbackend/tensorflow/libhybridbackend_tensorflow.so
hybridbackend/tensorflow/__init__.py
hybridbackend/tensorflow/data/iterators.py
hybridbackend/tensorflow/data/__init__.py
hybridbackend/tensorflow/data/dataframe.py
hybridbackend/tensorflow/data/rebatch/__init__.py
hybridbackend/tensorflow/data/rebatch/dataset_v1.py
hybridbackend/tensorflow/data/rebatch/dataset.py
hybridbackend/tensorflow/data/rebatch/dataset_v2.py
hybridbackend/tensorflow/data/sync/__init__.py
hybridbackend/tensorflow/data/sync/hook.py
hybridbackend/tensorflow/data/sync/dataset_v1.py
hybridbackend/tensorflow/data/sync/dataset.py
hybridbackend/tensorflow/data/sync/dataset_v2.py
hybridbackend/tensorflow/data/prefetch/__init__.py
hybridbackend/tensorflow/data/prefetch/iterator.py
hybridbackend/tensorflow/data/parquet/benchmark.py
hybridbackend/tensorflow/data/parquet/schema.py
hybridbackend/tensorflow/data/parquet/__init__.py
hybridbackend/tensorflow/data/parquet/dataset_v1.py
hybridbackend/tensorflow/data/parquet/dataset.py
hybridbackend/tensorflow/data/parquet/validate.py
hybridbackend/tensorflow/data/parquet/dataset_v2.py
hybridbackend/tensorflow/data/parquet/benchmark_mock.py
hybridbackend/tensorflow/estimator/estimator.py
hybridbackend/tensorflow/estimator/__init__.py
hybridbackend/tensorflow/pipeline/benchmark.py
hybridbackend/tensorflow/pipeline/pipeline_lib.c
hybridbackend/tensorflow/pipeline/__init__.py
hybridbackend/tensorflow/pipeline/pipeline_lib.cpython-38-x86_64-linux-gnu.so
hybridbackend/tensorflow/keras/model.py
hybridbackend/tensorflow/keras/__init__.py
hybridbackend/tensorflow/keras/layers/__init__.py
hybridbackend/tensorflow/ops/__init__.py
hybridbackend/tensorflow/ops/floormod_shuffle/ops.py
hybridbackend_tf115_cu116-0.7.0.dev1672506489.dist-info/top_level.txt
hybridbackend_tf115_cu116-0.7.0.dev1672506489.dist-info/RECORD
hybridbackend_tf115_cu116-0.7.0.dev1672506489.dist-info/NOTICE
hybridbackend_tf115_cu116-0.7.0.dev1672506489.dist-info/LICENSE
hybridbackend_tf115_cu116-0.7.0.dev1672506489.dist-info/METADATA
hybridbackend_tf115_cu116-0.7.0.dev1672506489.dist-info/WHEEL
