Metadata-Version: 2.1
Name: hybridbackend-tf115-cu116
Version: 0.7.0.dev1672506489
Summary: A high-performance framework for training wide-and-deep recommender systems on heterogeneous cluster
Home-page: https://github.com/alibaba/HybridBackend
Download-URL: https://github.com/alibaba/HybridBackend/tags
Author: Alibaba Group Holding Limited
License: Apache License 2.0
Project-URL: Bug Tracker, https://github.com/alibaba/HybridBackend/issues
Project-URL: Documentation, https://hybridbackend.readthedocs.io/en/latest/
Project-URL: Source Code, https://github.com/alibaba/HybridBackend
Keywords: deep learning,recommendation system
Classifier: Development Status :: 5 - Production/Stable
Classifier: Intended Audience :: Developers
Classifier: Intended Audience :: Science/Research
Classifier: License :: OSI Approved :: Apache Software License
Classifier: Programming Language :: Python :: 3.6
Classifier: Operating System :: POSIX :: Linux
Classifier: Topic :: Scientific/Engineering :: Artificial Intelligence
Classifier: Topic :: Software Development :: Libraries :: Python Modules
Classifier: Topic :: Software Development :: Libraries
License-File: LICENSE
License-File: NOTICE
Requires-Dist: nvidia-tensorflow
